{
    "Adversarial model":{
        "validation_accuracy":0.5927601809954751,
        "test_accuracy":0.5720026791694575
    },
    "Weak model":{
        "num_weak_signal":1,
        "validation_accuracy":[
            0.5701357466063348
        ],
        "test_accuracy":[
            0.5706630944407234
        ],
        "baseline_val_accuracy":[
            0.5701357466063348
        ],
        "baseline_test_accuracy":[
            0.5699933020763563
        ],
        "gecriteria_val_accuracy":0.4419306184012066,
        "gecriteria_test_accuracy":0.4554588077695914
    }
}{
    "Adversarial model":{
        "validation_accuracy":0.5902463549522373,
        "test_accuracy":0.6222371064969859
    },
    "Weak model":{
        "num_weak_signal":2,
        "validation_accuracy":[
            0.5701357466063348,
            0.5867269984917044
        ],
        "test_accuracy":[
            0.5706630944407234,
            0.5961152042866711
        ],
        "baseline_val_accuracy":[
            0.5827048768225239
        ],
        "baseline_test_accuracy":[
            0.5733422638981915
        ],
        "gecriteria_val_accuracy":0.43790849673202614,
        "gecriteria_test_accuracy":0.42665773610180846
    }
}{
    "Adversarial model":{
        "validation_accuracy":0.5902463549522373,
        "test_accuracy":0.622906898861353
    },
    "Weak model":{
        "num_weak_signal":3,
        "validation_accuracy":[
            0.5701357466063348,
            0.5867269984917044,
            0.5701357466063348
        ],
        "test_accuracy":[
            0.5706630944407234,
            0.5961152042866711,
            0.5699933020763563
        ],
        "baseline_val_accuracy":[
            0.5786827551533434
        ],
        "baseline_test_accuracy":[
            0.5552578700602813
        ],
        "gecriteria_val_accuracy":0.477124183006536,
        "gecriteria_test_accuracy":0.4246483590087073
    }
}{
    "Adversarial model":{
        "validation_accuracy":0.5942684766214178,
        "test_accuracy":0.565974547890154
    },
    "Weak model":{
        "num_weak_signal":1,
        "validation_accuracy":[
            0.5701357466063348
        ],
        "test_accuracy":[
            0.5706630944407234
        ],
        "baseline_val_accuracy":[
            0.5701357466063348
        ],
        "baseline_test_accuracy":[
            0.5699933020763563
        ],
        "gecriteria_val_accuracy":0.4419306184012066,
        "gecriteria_test_accuracy":0.4554588077695914
    }
}{
    "Adversarial model":{
        "validation_accuracy":0.5776772247360482,
        "test_accuracy":0.6034829202947086
    },
    "Weak model":{
        "num_weak_signal":2,
        "validation_accuracy":[
            0.5701357466063348,
            0.5867269984917044
        ],
        "test_accuracy":[
            0.5706630944407234,
            0.5961152042866711
        ],
        "baseline_val_accuracy":[
            0.5827048768225239
        ],
        "baseline_test_accuracy":[
            0.5733422638981915
        ],
        "gecriteria_val_accuracy":0.43790849673202614,
        "gecriteria_test_accuracy":0.42665773610180846
    }
}{
    "Adversarial model":{
        "validation_accuracy":0.5786827551533434,
        "test_accuracy":0.59410582719357
    },
    "Weak model":{
        "num_weak_signal":3,
        "validation_accuracy":[
            0.5701357466063348,
            0.5867269984917044,
            0.5701357466063348
        ],
        "test_accuracy":[
            0.5706630944407234,
            0.5961152042866711,
            0.5699933020763563
        ],
        "baseline_val_accuracy":[
            0.5786827551533434
        ],
        "baseline_test_accuracy":[
            0.5552578700602813
        ],
        "gecriteria_val_accuracy":0.5082956259426847,
        "gecriteria_test_accuracy":0.5257870060281313
    }
}{
    "Adversarial model":{
        "validation_accuracy":0.5927601809954751,
        "test_accuracy":0.5720026791694575
    },
    "Weak model":{
        "num_weak_signal":1,
        "validation_accuracy":[
            0.5701357466063348
        ],
        "test_accuracy":[
            0.5706630944407234
        ],
        "baseline_val_accuracy":[
            0.5701357466063348
        ],
        "baseline_test_accuracy":[
            0.5699933020763563
        ],
        "gecriteria_val_accuracy":0.4419306184012066,
        "gecriteria_test_accuracy":0.4554588077695914
    }
}{
    "Adversarial model":{
        "validation_accuracy":0.5902463549522373,
        "test_accuracy":0.6222371064969859
    },
    "Weak model":{
        "num_weak_signal":2,
        "validation_accuracy":[
            0.5701357466063348,
            0.5867269984917044
        ],
        "test_accuracy":[
            0.5706630944407234,
            0.5961152042866711
        ],
        "baseline_val_accuracy":[
            0.5827048768225239
        ],
        "baseline_test_accuracy":[
            0.5733422638981915
        ],
        "gecriteria_val_accuracy":0.43790849673202614,
        "gecriteria_test_accuracy":0.42665773610180846
    }
}{
    "Adversarial model":{
        "validation_accuracy":0.5902463549522373,
        "test_accuracy":0.622906898861353
    },
    "Weak model":{
        "num_weak_signal":3,
        "validation_accuracy":[
            0.5701357466063348,
            0.5867269984917044,
            0.5701357466063348
        ],
        "test_accuracy":[
            0.5706630944407234,
            0.5961152042866711,
            0.5699933020763563
        ],
        "baseline_val_accuracy":[
            0.5786827551533434
        ],
        "baseline_test_accuracy":[
            0.5552578700602813
        ],
        "gecriteria_val_accuracy":0.48265460030165913,
        "gecriteria_test_accuracy":0.4722036168787676
    }
}{
    "Adversarial model":{
        "validation_accuracy":0.5942684766214178,
        "test_accuracy":0.565974547890154
    },
    "Weak model":{
        "num_weak_signal":1,
        "validation_accuracy":[
            0.5701357466063348
        ],
        "test_accuracy":[
            0.5706630944407234
        ],
        "baseline_val_accuracy":[
            0.5701357466063348
        ],
        "baseline_test_accuracy":[
            0.5699933020763563
        ],
        "gecriteria_val_accuracy":0.4419306184012066,
        "gecriteria_test_accuracy":0.4554588077695914
    }
}{
    "Adversarial model":{
        "validation_accuracy":0.5776772247360482,
        "test_accuracy":0.6034829202947086
    },
    "Weak model":{
        "num_weak_signal":2,
        "validation_accuracy":[
            0.5701357466063348,
            0.5867269984917044
        ],
        "test_accuracy":[
            0.5706630944407234,
            0.5961152042866711
        ],
        "baseline_val_accuracy":[
            0.5827048768225239
        ],
        "baseline_test_accuracy":[
            0.5733422638981915
        ],
        "gecriteria_val_accuracy":0.43790849673202614,
        "gecriteria_test_accuracy":0.42665773610180846
    }
}{
    "Adversarial model":{
        "validation_accuracy":0.5786827551533434,
        "test_accuracy":0.59410582719357
    },
    "Weak model":{
        "num_weak_signal":3,
        "validation_accuracy":[
            0.5701357466063348,
            0.5867269984917044,
            0.5701357466063348
        ],
        "test_accuracy":[
            0.5706630944407234,
            0.5961152042866711,
            0.5699933020763563
        ],
        "baseline_val_accuracy":[
            0.5786827551533434
        ],
        "baseline_test_accuracy":[
            0.5552578700602813
        ],
        "gecriteria_val_accuracy":0.4625439919557567,
        "gecriteria_test_accuracy":0.4547890154052244
    }
}{
    "Adversarial model":{
        "validation_accuracy":0.5927601809954751,
        "test_accuracy":0.5720026791694575
    },
    "Weak model":{
        "num_weak_signal":1,
        "validation_accuracy":[
            0.5701357466063348
        ],
        "test_accuracy":[
            0.5706630944407234
        ],
        "baseline_val_accuracy":[
            0.5701357466063348
        ],
        "baseline_test_accuracy":[
            0.5699933020763563
        ],
        "gecriteria_val_accuracy":0.4419306184012066,
        "gecriteria_test_accuracy":0.4554588077695914
    }
}{
    "Adversarial model":{
        "validation_accuracy":0.5902463549522373,
        "test_accuracy":0.6222371064969859
    },
    "Weak model":{
        "num_weak_signal":2,
        "validation_accuracy":[
            0.5701357466063348,
            0.5867269984917044
        ],
        "test_accuracy":[
            0.5706630944407234,
            0.5961152042866711
        ],
        "baseline_val_accuracy":[
            0.5827048768225239
        ],
        "baseline_test_accuracy":[
            0.5733422638981915
        ],
        "gecriteria_val_accuracy":0.43790849673202614,
        "gecriteria_test_accuracy":0.42665773610180846
    }
}{
    "Adversarial model":{
        "validation_accuracy":0.5902463549522373,
        "test_accuracy":0.622906898861353
    },
    "Weak model":{
        "num_weak_signal":3,
        "validation_accuracy":[
            0.5701357466063348,
            0.5867269984917044,
            0.5701357466063348
        ],
        "test_accuracy":[
            0.5706630944407234,
            0.5961152042866711,
            0.5699933020763563
        ],
        "baseline_val_accuracy":[
            0.5786827551533434
        ],
        "baseline_test_accuracy":[
            0.5552578700602813
        ],
        "gecriteria_val_accuracy":0.5429864253393665,
        "gecriteria_test_accuracy":0.5311453449430676
    }
}{
    "Adversarial model":{
        "validation_accuracy":0.5942684766214178,
        "test_accuracy":0.565974547890154
    },
    "Weak model":{
        "num_weak_signal":1,
        "validation_accuracy":[
            0.5701357466063348
        ],
        "test_accuracy":[
            0.5706630944407234
        ],
        "baseline_val_accuracy":[
            0.5701357466063348
        ],
        "baseline_test_accuracy":[
            0.5699933020763563
        ],
        "gecriteria_val_accuracy":0.4419306184012066,
        "gecriteria_test_accuracy":0.4554588077695914
    }
}{
    "Adversarial model":{
        "validation_accuracy":0.5776772247360482,
        "test_accuracy":0.6034829202947086
    },
    "Weak model":{
        "num_weak_signal":2,
        "validation_accuracy":[
            0.5701357466063348,
            0.5867269984917044
        ],
        "test_accuracy":[
            0.5706630944407234,
            0.5961152042866711
        ],
        "baseline_val_accuracy":[
            0.5827048768225239
        ],
        "baseline_test_accuracy":[
            0.5733422638981915
        ],
        "gecriteria_val_accuracy":0.43790849673202614,
        "gecriteria_test_accuracy":0.42665773610180846
    }
}{
    "Adversarial model":{
        "validation_accuracy":0.5786827551533434,
        "test_accuracy":0.59410582719357
    },
    "Weak model":{
        "num_weak_signal":3,
        "validation_accuracy":[
            0.5701357466063348,
            0.5867269984917044,
            0.5701357466063348
        ],
        "test_accuracy":[
            0.5706630944407234,
            0.5961152042866711,
            0.5699933020763563
        ],
        "baseline_val_accuracy":[
            0.5786827551533434
        ],
        "baseline_test_accuracy":[
            0.5552578700602813
        ],
        "gecriteria_val_accuracy":0.44394167923579686,
        "gecriteria_test_accuracy":0.4554588077695914
    }
}{
    "Adversarial model":{
        "validation_accuracy":0.5927601809954751,
        "test_accuracy":0.5720026791694575
    },
    "Weak model":{
        "num_weak_signal":1,
        "validation_accuracy":[
            0.5701357466063348
        ],
        "test_accuracy":[
            0.5706630944407234
        ],
        "baseline_val_accuracy":[
            0.5701357466063348
        ],
        "baseline_test_accuracy":[
            0.5699933020763563
        ],
        "gecriteria_val_accuracy":0.4419306184012066,
        "gecriteria_test_accuracy":0.4554588077695914
    }
}{
    "Adversarial model":{
        "validation_accuracy":0.5902463549522373,
        "test_accuracy":0.6222371064969859
    },
    "Weak model":{
        "num_weak_signal":2,
        "validation_accuracy":[
            0.5701357466063348,
            0.5867269984917044
        ],
        "test_accuracy":[
            0.5706630944407234,
            0.5961152042866711
        ],
        "baseline_val_accuracy":[
            0.5827048768225239
        ],
        "baseline_test_accuracy":[
            0.5733422638981915
        ],
        "gecriteria_val_accuracy":0.43790849673202614,
        "gecriteria_test_accuracy":0.42665773610180846
    }
}{
    "Adversarial model":{
        "validation_accuracy":0.5902463549522373,
        "test_accuracy":0.622906898861353
    },
    "Weak model":{
        "num_weak_signal":3,
        "validation_accuracy":[
            0.5701357466063348,
            0.5867269984917044,
            0.5701357466063348
        ],
        "test_accuracy":[
            0.5706630944407234,
            0.5961152042866711,
            0.5699933020763563
        ],
        "baseline_val_accuracy":[
            0.5786827551533434
        ],
        "baseline_test_accuracy":[
            0.5552578700602813
        ],
        "gecriteria_val_accuracy":0.42835595776772245,
        "gecriteria_test_accuracy":0.4514400535833891
    }
}{
    "Adversarial model":{
        "validation_accuracy":0.5942684766214178,
        "test_accuracy":0.565974547890154
    },
    "Weak model":{
        "num_weak_signal":1,
        "validation_accuracy":[
            0.5701357466063348
        ],
        "test_accuracy":[
            0.5706630944407234
        ],
        "baseline_val_accuracy":[
            0.5701357466063348
        ],
        "baseline_test_accuracy":[
            0.5699933020763563
        ],
        "gecriteria_val_accuracy":0.4419306184012066,
        "gecriteria_test_accuracy":0.4554588077695914
    }
}{
    "Adversarial model":{
        "validation_accuracy":0.5776772247360482,
        "test_accuracy":0.6034829202947086
    },
    "Weak model":{
        "num_weak_signal":2,
        "validation_accuracy":[
            0.5701357466063348,
            0.5867269984917044
        ],
        "test_accuracy":[
            0.5706630944407234,
            0.5961152042866711
        ],
        "baseline_val_accuracy":[
            0.5827048768225239
        ],
        "baseline_test_accuracy":[
            0.5733422638981915
        ],
        "gecriteria_val_accuracy":0.43790849673202614,
        "gecriteria_test_accuracy":0.42665773610180846
    }
}{
    "Adversarial model":{
        "validation_accuracy":0.5786827551533434,
        "test_accuracy":0.59410582719357
    },
    "Weak model":{
        "num_weak_signal":3,
        "validation_accuracy":[
            0.5701357466063348,
            0.5867269984917044,
            0.5701357466063348
        ],
        "test_accuracy":[
            0.5706630944407234,
            0.5961152042866711,
            0.5699933020763563
        ],
        "baseline_val_accuracy":[
            0.5786827551533434
        ],
        "baseline_test_accuracy":[
            0.5552578700602813
        ],
        "gecriteria_val_accuracy":0.48969331322272497,
        "gecriteria_test_accuracy":0.4842598794373744
    }
}{
    "Adversarial model":{
        "validation_accuracy":0.5927601809954751,
        "test_accuracy":0.5720026791694575
    },
    "Weak model":{
        "num_weak_signal":1,
        "validation_accuracy":[
            0.5701357466063348
        ],
        "test_accuracy":[
            0.5706630944407234
        ],
        "baseline_val_accuracy":[
            0.5701357466063348
        ],
        "baseline_test_accuracy":[
            0.5699933020763563
        ],
        "gecriteria_val_accuracy":0.4419306184012066,
        "gecriteria_test_accuracy":0.4554588077695914
    }
}{
    "Adversarial model":{
        "validation_accuracy":0.5902463549522373,
        "test_accuracy":0.6222371064969859
    },
    "Weak model":{
        "num_weak_signal":2,
        "validation_accuracy":[
            0.5701357466063348,
            0.5867269984917044
        ],
        "test_accuracy":[
            0.5706630944407234,
            0.5961152042866711
        ],
        "baseline_val_accuracy":[
            0.5827048768225239
        ],
        "baseline_test_accuracy":[
            0.5733422638981915
        ],
        "gecriteria_val_accuracy":0.43790849673202614,
        "gecriteria_test_accuracy":0.42665773610180846
    }
}{
    "Adversarial model":{
        "validation_accuracy":0.5902463549522373,
        "test_accuracy":0.622906898861353
    },
    "Weak model":{
        "num_weak_signal":3,
        "validation_accuracy":[
            0.5701357466063348,
            0.5867269984917044,
            0.5701357466063348
        ],
        "test_accuracy":[
            0.5706630944407234,
            0.5961152042866711,
            0.5699933020763563
        ],
        "baseline_val_accuracy":[
            0.5786827551533434
        ],
        "baseline_test_accuracy":[
            0.5552578700602813
        ],
        "gecriteria_val_accuracy":0.43790849673202614,
        "gecriteria_test_accuracy":0.434695244474213
    }
}{
    "Adversarial model":{
        "validation_accuracy":0.5942684766214178,
        "test_accuracy":0.565974547890154
    },
    "Weak model":{
        "num_weak_signal":1,
        "validation_accuracy":[
            0.5701357466063348
        ],
        "test_accuracy":[
            0.5706630944407234
        ],
        "baseline_val_accuracy":[
            0.5701357466063348
        ],
        "baseline_test_accuracy":[
            0.5699933020763563
        ],
        "gecriteria_val_accuracy":0.4419306184012066,
        "gecriteria_test_accuracy":0.4554588077695914
    }
}{
    "Adversarial model":{
        "validation_accuracy":0.5776772247360482,
        "test_accuracy":0.6034829202947086
    },
    "Weak model":{
        "num_weak_signal":2,
        "validation_accuracy":[
            0.5701357466063348,
            0.5867269984917044
        ],
        "test_accuracy":[
            0.5706630944407234,
            0.5961152042866711
        ],
        "baseline_val_accuracy":[
            0.5827048768225239
        ],
        "baseline_test_accuracy":[
            0.5733422638981915
        ],
        "gecriteria_val_accuracy":0.43790849673202614,
        "gecriteria_test_accuracy":0.42665773610180846
    }
}{
    "Adversarial model":{
        "validation_accuracy":0.5786827551533434,
        "test_accuracy":0.59410582719357
    },
    "Weak model":{
        "num_weak_signal":3,
        "validation_accuracy":[
            0.5701357466063348,
            0.5867269984917044,
            0.5701357466063348
        ],
        "test_accuracy":[
            0.5706630944407234,
            0.5961152042866711,
            0.5699933020763563
        ],
        "baseline_val_accuracy":[
            0.5786827551533434
        ],
        "baseline_test_accuracy":[
            0.5552578700602813
        ],
        "gecriteria_val_accuracy":0.4494720965309201,
        "gecriteria_test_accuracy":0.4393837910247823
    }
}{
    "Adversarial model":{
        "validation_accuracy":0.5927601809954751,
        "test_accuracy":0.5720026791694575
    },
    "Weak model":{
        "num_weak_signal":1,
        "validation_accuracy":[
            0.5701357466063348
        ],
        "test_accuracy":[
            0.5706630944407234
        ],
        "baseline_val_accuracy":[
            0.5701357466063348
        ],
        "baseline_test_accuracy":[
            0.5699933020763563
        ],
        "gecriteria_val_accuracy":0.4419306184012066,
        "gecriteria_test_accuracy":0.4554588077695914
    }
}{
    "Adversarial model":{
        "validation_accuracy":0.5902463549522373,
        "test_accuracy":0.6222371064969859
    },
    "Weak model":{
        "num_weak_signal":2,
        "validation_accuracy":[
            0.5701357466063348,
            0.5867269984917044
        ],
        "test_accuracy":[
            0.5706630944407234,
            0.5961152042866711
        ],
        "baseline_val_accuracy":[
            0.5827048768225239
        ],
        "baseline_test_accuracy":[
            0.5733422638981915
        ],
        "gecriteria_val_accuracy":0.43790849673202614,
        "gecriteria_test_accuracy":0.42665773610180846
    }
}{
    "Adversarial model":{
        "validation_accuracy":0.5902463549522373,
        "test_accuracy":0.622906898861353
    },
    "Weak model":{
        "num_weak_signal":3,
        "validation_accuracy":[
            0.5701357466063348,
            0.5867269984917044,
            0.5701357466063348
        ],
        "test_accuracy":[
            0.5706630944407234,
            0.5961152042866711,
            0.5699933020763563
        ],
        "baseline_val_accuracy":[
            0.5786827551533434
        ],
        "baseline_test_accuracy":[
            0.5552578700602813
        ],
        "gecriteria_val_accuracy":0.49019607843137253,
        "gecriteria_test_accuracy":0.4675150703281983
    }
}{
    "Adversarial model":{
        "validation_accuracy":0.5942684766214178,
        "test_accuracy":0.565974547890154
    },
    "Weak model":{
        "num_weak_signal":1,
        "validation_accuracy":[
            0.5701357466063348
        ],
        "test_accuracy":[
            0.5706630944407234
        ],
        "baseline_val_accuracy":[
            0.5701357466063348
        ],
        "baseline_test_accuracy":[
            0.5699933020763563
        ],
        "gecriteria_val_accuracy":0.4419306184012066,
        "gecriteria_test_accuracy":0.4554588077695914
    }
}{
    "Adversarial model":{
        "validation_accuracy":0.5776772247360482,
        "test_accuracy":0.6034829202947086
    },
    "Weak model":{
        "num_weak_signal":2,
        "validation_accuracy":[
            0.5701357466063348,
            0.5867269984917044
        ],
        "test_accuracy":[
            0.5706630944407234,
            0.5961152042866711
        ],
        "baseline_val_accuracy":[
            0.5827048768225239
        ],
        "baseline_test_accuracy":[
            0.5733422638981915
        ],
        "gecriteria_val_accuracy":0.43790849673202614,
        "gecriteria_test_accuracy":0.42665773610180846
    }
}{
    "Adversarial model":{
        "validation_accuracy":0.5786827551533434,
        "test_accuracy":0.59410582719357
    },
    "Weak model":{
        "num_weak_signal":3,
        "validation_accuracy":[
            0.5701357466063348,
            0.5867269984917044,
            0.5701357466063348
        ],
        "test_accuracy":[
            0.5706630944407234,
            0.5961152042866711,
            0.5699933020763563
        ],
        "baseline_val_accuracy":[
            0.5786827551533434
        ],
        "baseline_test_accuracy":[
            0.5552578700602813
        ],
        "gecriteria_val_accuracy":0.47410759175465056,
        "gecriteria_test_accuracy":0.46282652377762895
    }
}{
    "Adversarial model":{
        "validation_accuracy":0.5927601809954751,
        "test_accuracy":0.5720026791694575
    },
    "Weak model":{
        "num_weak_signal":1,
        "validation_accuracy":[
            0.5701357466063348
        ],
        "test_accuracy":[
            0.5706630944407234
        ],
        "baseline_val_accuracy":[
            0.5701357466063348
        ],
        "baseline_test_accuracy":[
            0.5699933020763563
        ],
        "gecriteria_val_accuracy":0.4419306184012066,
        "gecriteria_test_accuracy":0.4554588077695914
    }
}{
    "Adversarial model":{
        "validation_accuracy":0.5902463549522373,
        "test_accuracy":0.6222371064969859
    },
    "Weak model":{
        "num_weak_signal":2,
        "validation_accuracy":[
            0.5701357466063348,
            0.5867269984917044
        ],
        "test_accuracy":[
            0.5706630944407234,
            0.5961152042866711
        ],
        "baseline_val_accuracy":[
            0.5827048768225239
        ],
        "baseline_test_accuracy":[
            0.5733422638981915
        ],
        "gecriteria_val_accuracy":0.43790849673202614,
        "gecriteria_test_accuracy":0.42665773610180846
    }
}{
    "Adversarial model":{
        "validation_accuracy":0.5902463549522373,
        "test_accuracy":0.622906898861353
    },
    "Weak model":{
        "num_weak_signal":3,
        "validation_accuracy":[
            0.5701357466063348,
            0.5867269984917044,
            0.5701357466063348
        ],
        "test_accuracy":[
            0.5706630944407234,
            0.5961152042866711,
            0.5699933020763563
        ],
        "baseline_val_accuracy":[
            0.5786827551533434
        ],
        "baseline_test_accuracy":[
            0.5552578700602813
        ],
        "gecriteria_val_accuracy":0.41478129713423834,
        "gecriteria_test_accuracy":0.39584728734092434
    }
}{
    "Adversarial model":{
        "validation_accuracy":0.5942684766214178,
        "test_accuracy":0.565974547890154
    },
    "Weak model":{
        "num_weak_signal":1,
        "validation_accuracy":[
            0.5701357466063348
        ],
        "test_accuracy":[
            0.5706630944407234
        ],
        "baseline_val_accuracy":[
            0.5701357466063348
        ],
        "baseline_test_accuracy":[
            0.5699933020763563
        ],
        "gecriteria_val_accuracy":0.4419306184012066,
        "gecriteria_test_accuracy":0.4554588077695914
    }
}{
    "Adversarial model":{
        "validation_accuracy":0.5776772247360482,
        "test_accuracy":0.6034829202947086
    },
    "Weak model":{
        "num_weak_signal":2,
        "validation_accuracy":[
            0.5701357466063348,
            0.5867269984917044
        ],
        "test_accuracy":[
            0.5706630944407234,
            0.5961152042866711
        ],
        "baseline_val_accuracy":[
            0.5827048768225239
        ],
        "baseline_test_accuracy":[
            0.5733422638981915
        ],
        "gecriteria_val_accuracy":0.43790849673202614,
        "gecriteria_test_accuracy":0.42665773610180846
    }
}{
    "Adversarial model":{
        "validation_accuracy":0.5786827551533434,
        "test_accuracy":0.59410582719357
    },
    "Weak model":{
        "num_weak_signal":3,
        "validation_accuracy":[
            0.5701357466063348,
            0.5867269984917044,
            0.5701357466063348
        ],
        "test_accuracy":[
            0.5706630944407234,
            0.5961152042866711,
            0.5699933020763563
        ],
        "baseline_val_accuracy":[
            0.5786827551533434
        ],
        "baseline_test_accuracy":[
            0.5552578700602813
        ],
        "gecriteria_val_accuracy":0.46304675716440424,
        "gecriteria_test_accuracy":0.43536503683858
    }
}{
    "Adversarial model":{
        "validation_accuracy":0.5927601809954751,
        "test_accuracy":0.5720026791694575
    },
    "Weak model":{
        "num_weak_signal":1,
        "validation_accuracy":[
            0.5701357466063348
        ],
        "test_accuracy":[
            0.5706630944407234
        ],
        "baseline_val_accuracy":[
            0.5701357466063348
        ],
        "baseline_test_accuracy":[
            0.5699933020763563
        ],
        "gecriteria_val_accuracy":0.4419306184012066,
        "gecriteria_test_accuracy":0.4554588077695914
    }
}{
    "Adversarial model":{
        "validation_accuracy":0.5902463549522373,
        "test_accuracy":0.6222371064969859
    },
    "Weak model":{
        "num_weak_signal":2,
        "validation_accuracy":[
            0.5701357466063348,
            0.5867269984917044
        ],
        "test_accuracy":[
            0.5706630944407234,
            0.5961152042866711
        ],
        "baseline_val_accuracy":[
            0.5827048768225239
        ],
        "baseline_test_accuracy":[
            0.5733422638981915
        ],
        "gecriteria_val_accuracy":0.43790849673202614,
        "gecriteria_test_accuracy":0.42665773610180846
    }
}{
    "Adversarial model":{
        "validation_accuracy":0.5902463549522373,
        "test_accuracy":0.622906898861353
    },
    "Weak model":{
        "num_weak_signal":3,
        "validation_accuracy":[
            0.5701357466063348,
            0.5867269984917044,
            0.5701357466063348
        ],
        "test_accuracy":[
            0.5706630944407234,
            0.5961152042866711,
            0.5699933020763563
        ],
        "baseline_val_accuracy":[
            0.5786827551533434
        ],
        "baseline_test_accuracy":[
            0.5552578700602813
        ],
        "gecriteria_val_accuracy":0.46304675716440424,
        "gecriteria_test_accuracy":0.4333556597454789
    }
}{
    "Adversarial model":{
        "validation_accuracy":0.5942684766214178,
        "test_accuracy":0.565974547890154
    },
    "Weak model":{
        "num_weak_signal":1,
        "validation_accuracy":[
            0.5701357466063348
        ],
        "test_accuracy":[
            0.5706630944407234
        ],
        "baseline_val_accuracy":[
            0.5701357466063348
        ],
        "baseline_test_accuracy":[
            0.5699933020763563
        ],
        "gecriteria_val_accuracy":0.4419306184012066,
        "gecriteria_test_accuracy":0.4554588077695914
    }
}{
    "Adversarial model":{
        "validation_accuracy":0.5776772247360482,
        "test_accuracy":0.6034829202947086
    },
    "Weak model":{
        "num_weak_signal":2,
        "validation_accuracy":[
            0.5701357466063348,
            0.5867269984917044
        ],
        "test_accuracy":[
            0.5706630944407234,
            0.5961152042866711
        ],
        "baseline_val_accuracy":[
            0.5827048768225239
        ],
        "baseline_test_accuracy":[
            0.5733422638981915
        ],
        "gecriteria_val_accuracy":0.43790849673202614,
        "gecriteria_test_accuracy":0.42665773610180846
    }
}{
    "Adversarial model":{
        "validation_accuracy":0.5786827551533434,
        "test_accuracy":0.59410582719357
    },
    "Weak model":{
        "num_weak_signal":3,
        "validation_accuracy":[
            0.5701357466063348,
            0.5867269984917044,
            0.5701357466063348
        ],
        "test_accuracy":[
            0.5706630944407234,
            0.5961152042866711,
            0.5699933020763563
        ],
        "baseline_val_accuracy":[
            0.5786827551533434
        ],
        "baseline_test_accuracy":[
            0.5552578700602813
        ],
        "gecriteria_val_accuracy":0.5123177476118652,
        "gecriteria_test_accuracy":0.4655056932350971
    }
}{
    "Adversarial model":{
        "validation_accuracy":0.5927601809954751,
        "test_accuracy":0.5720026791694575
    },
    "Weak model":{
        "num_weak_signal":1,
        "validation_accuracy":[
            0.5701357466063348
        ],
        "test_accuracy":[
            0.5706630944407234
        ],
        "baseline_val_accuracy":[
            0.5701357466063348
        ],
        "baseline_test_accuracy":[
            0.5699933020763563
        ],
        "gecriteria_val_accuracy":0.4419306184012066,
        "gecriteria_test_accuracy":0.4554588077695914
    }
}{
    "Adversarial model":{
        "validation_accuracy":0.5902463549522373,
        "test_accuracy":0.6222371064969859
    },
    "Weak model":{
        "num_weak_signal":2,
        "validation_accuracy":[
            0.5701357466063348,
            0.5867269984917044
        ],
        "test_accuracy":[
            0.5706630944407234,
            0.5961152042866711
        ],
        "baseline_val_accuracy":[
            0.5827048768225239
        ],
        "baseline_test_accuracy":[
            0.5733422638981915
        ],
        "gecriteria_val_accuracy":0.43790849673202614,
        "gecriteria_test_accuracy":0.42665773610180846
    }
}{
    "Adversarial model":{
        "validation_accuracy":0.5902463549522373,
        "test_accuracy":0.622906898861353
    },
    "Weak model":{
        "num_weak_signal":3,
        "validation_accuracy":[
            0.5701357466063348,
            0.5867269984917044,
            0.5701357466063348
        ],
        "test_accuracy":[
            0.5706630944407234,
            0.5961152042866711,
            0.5699933020763563
        ],
        "baseline_val_accuracy":[
            0.5786827551533434
        ],
        "baseline_test_accuracy":[
            0.5552578700602813
        ],
        "gecriteria_val_accuracy":0.473604826546003,
        "gecriteria_test_accuracy":0.46282652377762895
    }
}{
    "Adversarial model":{
        "validation_accuracy":0.5942684766214178,
        "test_accuracy":0.565974547890154
    },
    "Weak model":{
        "num_weak_signal":1,
        "validation_accuracy":[
            0.5701357466063348
        ],
        "test_accuracy":[
            0.5706630944407234
        ],
        "baseline_val_accuracy":[
            0.5701357466063348
        ],
        "baseline_test_accuracy":[
            0.5699933020763563
        ],
        "gecriteria_val_accuracy":0.4419306184012066,
        "gecriteria_test_accuracy":0.4554588077695914
    }
}{
    "Adversarial model":{
        "validation_accuracy":0.5776772247360482,
        "test_accuracy":0.6034829202947086
    },
    "Weak model":{
        "num_weak_signal":2,
        "validation_accuracy":[
            0.5701357466063348,
            0.5867269984917044
        ],
        "test_accuracy":[
            0.5706630944407234,
            0.5961152042866711
        ],
        "baseline_val_accuracy":[
            0.5827048768225239
        ],
        "baseline_test_accuracy":[
            0.5733422638981915
        ],
        "gecriteria_val_accuracy":0.43790849673202614,
        "gecriteria_test_accuracy":0.42665773610180846
    }
}{
    "Adversarial model":{
        "validation_accuracy":0.5786827551533434,
        "test_accuracy":0.59410582719357
    },
    "Weak model":{
        "num_weak_signal":3,
        "validation_accuracy":[
            0.5701357466063348,
            0.5867269984917044,
            0.5701357466063348
        ],
        "test_accuracy":[
            0.5706630944407234,
            0.5961152042866711,
            0.5699933020763563
        ],
        "baseline_val_accuracy":[
            0.5786827551533434
        ],
        "baseline_test_accuracy":[
            0.5552578700602813
        ],
        "gecriteria_val_accuracy":0.47762694821518353,
        "gecriteria_test_accuracy":0.449430676490288
    }
}{
    "Adversarial model":{
        "validation_accuracy":0.5927601809954751,
        "test_accuracy":0.5720026791694575
    },
    "Weak model":{
        "num_weak_signal":1,
        "validation_accuracy":[
            0.5701357466063348
        ],
        "test_accuracy":[
            0.5706630944407234
        ],
        "baseline_val_accuracy":[
            0.5701357466063348
        ],
        "baseline_test_accuracy":[
            0.5699933020763563
        ],
        "gecriteria_val_accuracy":0.4419306184012066,
        "gecriteria_test_accuracy":0.4554588077695914
    }
}{
    "Adversarial model":{
        "validation_accuracy":0.5902463549522373,
        "test_accuracy":0.6222371064969859
    },
    "Weak model":{
        "num_weak_signal":2,
        "validation_accuracy":[
            0.5701357466063348,
            0.5867269984917044
        ],
        "test_accuracy":[
            0.5706630944407234,
            0.5961152042866711
        ],
        "baseline_val_accuracy":[
            0.5827048768225239
        ],
        "baseline_test_accuracy":[
            0.5733422638981915
        ],
        "gecriteria_val_accuracy":0.43790849673202614,
        "gecriteria_test_accuracy":0.42665773610180846
    }
}{
    "Adversarial model":{
        "validation_accuracy":0.5902463549522373,
        "test_accuracy":0.622906898861353
    },
    "Weak model":{
        "num_weak_signal":3,
        "validation_accuracy":[
            0.5701357466063348,
            0.5867269984917044,
            0.5701357466063348
        ],
        "test_accuracy":[
            0.5706630944407234,
            0.5961152042866711,
            0.5699933020763563
        ],
        "baseline_val_accuracy":[
            0.5786827551533434
        ],
        "baseline_test_accuracy":[
            0.5552578700602813
        ],
        "gecriteria_val_accuracy":0.461035696329814,
        "gecriteria_test_accuracy":0.46885465505693236
    }
}{
    "Adversarial model":{
        "validation_accuracy":0.5942684766214178,
        "test_accuracy":0.565974547890154
    },
    "Weak model":{
        "num_weak_signal":1,
        "validation_accuracy":[
            0.5701357466063348
        ],
        "test_accuracy":[
            0.5706630944407234
        ],
        "baseline_val_accuracy":[
            0.5701357466063348
        ],
        "baseline_test_accuracy":[
            0.5699933020763563
        ],
        "gecriteria_val_accuracy":0.4419306184012066,
        "gecriteria_test_accuracy":0.4554588077695914
    }
}{
    "Adversarial model":{
        "validation_accuracy":0.5776772247360482,
        "test_accuracy":0.6034829202947086
    },
    "Weak model":{
        "num_weak_signal":2,
        "validation_accuracy":[
            0.5701357466063348,
            0.5867269984917044
        ],
        "test_accuracy":[
            0.5706630944407234,
            0.5961152042866711
        ],
        "baseline_val_accuracy":[
            0.5827048768225239
        ],
        "baseline_test_accuracy":[
            0.5733422638981915
        ],
        "gecriteria_val_accuracy":0.43790849673202614,
        "gecriteria_test_accuracy":0.42665773610180846
    }
}{
    "Adversarial model":{
        "validation_accuracy":0.5786827551533434,
        "test_accuracy":0.59410582719357
    },
    "Weak model":{
        "num_weak_signal":3,
        "validation_accuracy":[
            0.5701357466063348,
            0.5867269984917044,
            0.5701357466063348
        ],
        "test_accuracy":[
            0.5706630944407234,
            0.5961152042866711,
            0.5699933020763563
        ],
        "baseline_val_accuracy":[
            0.5786827551533434
        ],
        "baseline_test_accuracy":[
            0.5552578700602813
        ],
        "gecriteria_val_accuracy":0.46405228758169936,
        "gecriteria_test_accuracy":0.43536503683858
    }
}